README.md
setup.py
YiWu/MCTC.py
YiWu/__init__.py
YiWu.egg-info/PKG-INFO
YiWu.egg-info/SOURCES.txt
YiWu.egg-info/dependency_links.txt
YiWu.egg-info/top_level.txt